pln_search/__init__.py
pln_search/__main__.py
pln_search/api.py
pln_search/auth.py
pln_search/cli.py
pln_search/config.py
pln_search/formatters.py
pln_search/models.py
pln_search-0.1.3.dist-info/METADATA
pln_search-0.1.3.dist-info/WHEEL
pln_search-0.1.3.dist-info/entry_points.txt
pln_search-0.1.3.dist-info/licenses/LICENSE
pln_search-0.1.3.dist-info/RECORD
