Metadata-Version: 2.4
Name: pln-search
Version: 0.1.3
Summary: CLI tool for searching the Protocol Labs Network Directory
Project-URL: Homepage, https://github.com/dannyob/pln-search
Project-URL: Repository, https://github.com/dannyob/pln-search
Project-URL: Issues, https://github.com/dannyob/pln-search/issues
Author-email: Danny O'Brien <danny@spesh.com>
License: MIT
License-File: LICENSE
Keywords: cli,directory,filecoin,pln,protocol-labs,search
Classifier: Development Status :: 3 - Alpha
Classifier: License :: OSI Approved :: MIT License
Classifier: Operating System :: OS Independent
Classifier: Topic :: Internet :: WWW/HTTP :: Indexing/Search
Requires-Python: >=3.10
Requires-Dist: click>=8.1.0
Requires-Dist: platformdirs>=4.0.0
Requires-Dist: requests>=2.31.0
Requires-Dist: rich>=13.0.0
